<?xml version="1.0" encoding="UTF-8"?>
<classes xmlns="http://xml.phpdox.de/src#">
  <namespace name="Planeta\Autenticacao\Armazenamento">
    <class full="Planeta\Autenticacao\Armazenamento\NaoPersistente" name="NaoPersistente" final="false" abstract="false" start="6" end="29" xml="fonte/Planeta/Autenticacao/Armazenamento/NaoPersistente.php.xml" src="/Users/abdalacerqueira/Sites/php/planeta/fonte/Planeta/Autenticacao/Armazenamento/NaoPersistente.php">
      <implements interface="InterfaceArmazenamento" namespace="Planeta\Autenticacao\Armazenamento" full="Planeta\Autenticacao\Armazenamento\InterfaceArmazenamento"/>
    </class>
    <class full="Planeta\Autenticacao\Armazenamento\Sessao" name="Sessao" final="false" abstract="false" start="6" end="38" xml="fonte/Planeta/Autenticacao/Armazenamento/Sessao.php.xml" src="/Users/abdalacerqueira/Sites/php/planeta/fonte/Planeta/Autenticacao/Armazenamento/Sessao.php">
      <implements interface="InterfaceArmazenamento" namespace="Planeta\Autenticacao\Armazenamento" full="Planeta\Autenticacao\Armazenamento\InterfaceArmazenamento"/>
    </class>
  </namespace>
  <namespace name="Planeta\Autenticacao">
    <class full="Planeta\Autenticacao\Autenticacao" name="Autenticacao" final="false" abstract="false" start="7" end="56" xml="fonte/Planeta/Autenticacao/Autenticacao.php.xml" src="/Users/abdalacerqueira/Sites/php/planeta/fonte/Planeta/Autenticacao/Autenticacao.php"/>
  </namespace>
  <namespace name="Planeta\Banco">
    <class full="Planeta\Banco\Banco" name="Banco" final="false" abstract="false" start="6" end="35" xml="fonte/Planeta/Banco/Banco.php.xml" src="/Users/abdalacerqueira/Sites/php/planeta/fonte/Planeta/Banco/Banco.php"/>
    <class full="Planeta\Banco\Tabela" name="Tabela" final="false" abstract="false" start="4" end="100" xml="fonte/Planeta/Banco/Tabela.php.xml" src="/Users/abdalacerqueira/Sites/php/planeta/fonte/Planeta/Banco/Tabela.php"/>
  </namespace>
  <namespace name="Planeta\Mvc">
    <class full="Planeta\Mvc\Controlador" name="Controlador" final="false" abstract="false" start="4" end="42" xml="fonte/Planeta/Mvc/Controlador.php.xml" src="/Users/abdalacerqueira/Sites/php/planeta/fonte/Planeta/Mvc/Controlador.php"/>
    <class full="Planeta\Mvc\Mvc" name="Mvc" final="false" abstract="false" start="7" end="93" xml="fonte/Planeta/Mvc/Mvc.php.xml" src="/Users/abdalacerqueira/Sites/php/planeta/fonte/Planeta/Mvc/Mvc.php"/>
    <class full="Planeta\Mvc\Visao" name="Visao" final="false" abstract="false" start="6" end="40" xml="fonte/Planeta/Mvc/Visao.php.xml" src="/Users/abdalacerqueira/Sites/php/planeta/fonte/Planeta/Mvc/Visao.php"/>
  </namespace>
  <namespace name="Planeta\Mvc\Excecao">
    <class full="Planeta\Mvc\Excecao\AcaoNaoExiste" name="AcaoNaoExiste" final="false" abstract="false" start="6" end="7" xml="fonte/Planeta/Mvc/Excecao/AcaoNaoExiste.php.xml" src="/Users/abdalacerqueira/Sites/php/planeta/fonte/Planeta/Mvc/Excecao/AcaoNaoExiste.php">
      <extends class="DomainException" full="DomainException"/>
    </class>
    <class full="Planeta\Mvc\Excecao\ControladorNaoExiste" name="ControladorNaoExiste" final="false" abstract="false" start="6" end="7" xml="fonte/Planeta/Mvc/Excecao/ControladorNaoExiste.php.xml" src="/Users/abdalacerqueira/Sites/php/planeta/fonte/Planeta/Mvc/Excecao/ControladorNaoExiste.php">
      <extends class="DomainException" full="DomainException"/>
    </class>
    <class full="Planeta\Mvc\Excecao\VisaoNaoExiste" name="VisaoNaoExiste" final="false" abstract="false" start="6" end="7" xml="fonte/Planeta/Mvc/Excecao/VisaoNaoExiste.php.xml" src="/Users/abdalacerqueira/Sites/php/planeta/fonte/Planeta/Mvc/Excecao/VisaoNaoExiste.php">
      <extends class="DomainException" full="DomainException"/>
    </class>
  </namespace>
</classes>
